{"id":55904,"name":"Chuck E. Cheese's Playhouse","slug":"chuck-e-cheeses-playhouse","url":"https:\/\/www.igdb.com\/games\/chuck-e-cheeses-playhouse","created_at":1504264942585,"updated_at":1516582192005,"summary":"A Chuck E. Cheese-themed activity center for Nintendo DS.","collection":2955,"popularity":1.333333333333333,"games":[44242,18623,22470,29173,26145,22425,55689,55590,23867,22406],"tags":[268435469,536871306,536872060,536875054,536875280],"category":0,"keywords":[394,1148,4142,4368],"genres":[13],"cover":{"url":"\/\/images.igdb.com\/igdb\/image\/upload\/t_thumb\/wofjitylianrr2w435wz.jpg","cloudinary_id":"wofjitylianrr2w435wz","width":640,"height":574}}