{"id":50750,"name":"Machine World 2","slug":"machine-world-2","url":"https:\/\/www.igdb.com\/games\/machine-world-2","created_at":1500052801154,"updated_at":1522237321346,"summary":"Take control of a range of different machines and operate them in a unique environment. Each new game generates a new world, and it is yours to develop: Dig and build anything, anywhere! \n \nAll machines have been carefully modelled down to small details. They all have opening doors and hatches, switches that control fully simulated systems, and have realistic physics models. You climb into and onto the machines, watch battery and fuel levels, follow realistic procedures that mimic the real machines. Our goal is to make you think of these machines as your own.","rating":50,"popularity":1.666666666666667,"total_rating":50,"total_rating_count":1,"rating_count":1,"games":[28465,34919,33603,36962,55888,44087,65827,28277,32283,55308],"tags":[268435469,268435488],"category":0,"game_modes":[1],"genres":[13,32],"first_release_date":1498867200000,"status":4,"platforms":[6,14],"release_dates":[{"category":1,"platform":14,"date":1498867200000,"region":8,"human":"2017-Jul","y":2017,"m":7},{"category":1,"platform":6,"date":1498867200000,"region":8,"human":"2017-Jul","y":2017,"m":7}],"screenshots":[{"url":"\/\/images.igdb.com\/igdb\/image\/upload\/t_thumb\/eaprwdej7jlcbjipvzd9.jpg","cloudinary_id":"eaprwdej7jlcbjipvzd9","width":1920,"height":1080},{"url":"\/\/images.igdb.com\/igdb\/image\/upload\/t_thumb\/azidn5pvvuxuiokdwtx9.jpg","cloudinary_id":"azidn5pvvuxuiokdwtx9","width":1920,"height":1080},{"url":"\/\/images.igdb.com\/igdb\/image\/upload\/t_thumb\/rmhzhvcjiim6kdm4xmet.jpg","cloudinary_id":"rmhzhvcjiim6kdm4xmet","width":1920,"height":1080},{"url":"\/\/images.igdb.com\/igdb\/image\/upload\/t_thumb\/s1eriqygwfrhlrocd4mm.jpg","cloudinary_id":"s1eriqygwfrhlrocd4mm","width":1920,"height":1080},{"url":"\/\/images.igdb.com\/igdb\/image\/upload\/t_thumb\/kizjhmb3tiehxyn3emaa.jpg","cloudinary_id":"kizjhmb3tiehxyn3emaa","width":1754,"height":1080}],"cover":{"url":"\/\/images.igdb.com\/igdb\/image\/upload\/t_thumb\/dbtdprvlmdiusld08lk2.jpg","cloudinary_id":"dbtdprvlmdiusld08lk2","width":600,"height":800},"websites":[{"category":1,"url":"http:\/\/www.trinogames.com"},{"category":13,"url":"https:\/\/store.steampowered.com\/app\/650350"}],"external":{"steam":"650350"}}