{"id":55192,"name":"Gear.Club Unlimited","slug":"gear-dot-club-unlimited","url":"https:\/\/www.igdb.com\/games\/gear-dot-club-unlimited","created_at":1504104550763,"updated_at":1516563399093,"summary":"Gear.Club is much more than a quick adrenaline rush; it is an authentic world of cars. Realistic driving and racing experience, with fully simulated engines, powertrains, suspensions and aerodynamics.","popularity":22.33333333333333,"aggregated_rating":62.5,"aggregated_rating_count":5,"total_rating":62.5,"total_rating_count":5,"games":[27378,44178,71828,27553,40470,103018,80382,109292,75244,49423],"tags":[268435466,536875069],"category":0,"keywords":[4157],"genres":[10],"first_release_date":1511222400000,"pulse_count":9,"platforms":[130],"release_dates":[{"category":0,"platform":130,"date":1511222400000,"region":2,"human":"2017-Nov-21","y":2017,"m":11}],"screenshots":[{"url":"\/\/images.igdb.com\/igdb\/image\/upload\/t_thumb\/rlhqroybygoloiwdds53.jpg","cloudinary_id":"rlhqroybygoloiwdds53","width":670,"height":377}],"cover":{"url":"\/\/images.igdb.com\/igdb\/image\/upload\/t_thumb\/qkgrz9lrqgieuseno4kh.jpg","cloudinary_id":"qkgrz9lrqgieuseno4kh","width":600,"height":800},"esrb":{"rating":3},"websites":[{"category":12,"url":"https:\/\/play.google.com\/store\/apps\/details?id=com.edengames.GTSpirit"}]}