{"id":49777,"name":"Shin Kisekae Monogatari","slug":"shin-kisekae-monogatari","url":"https:\/\/www.igdb.com\/games\/shin-kisekae-monogatari","created_at":1500025551690,"updated_at":1500377491961,"summary":"Shin Kisekae Monogatari is an Adventure game, published by Marvelous Entertainment, which was released in Japan in 2003.","popularity":1,"games":[14605,17469,75586,25130,43130,23175,28277,63734,29646,27266],"tags":[268435487],"category":0,"genres":[31],"first_release_date":1065312000000,"platforms":[24],"release_dates":[{"category":0,"platform":24,"date":1065312000000,"region":8,"human":"2003-Oct-05","y":2003,"m":10}]}