{"id":85377,"name":"Skater Cat","slug":"skater-cat","url":"https:\/\/www.igdb.com\/games\/skater-cat","created_at":1517403074586,"updated_at":1518008966385,"summary":"Skater Cat is a side-scrolling action game where players jump on board a skateboard with Ollie the coolest cat in town.","popularity":1,"publishers":[709],"category":0,"first_release_date":1395878400000,"platforms":[37],"release_dates":[{"category":0,"platform":37,"date":1395878400000,"region":1,"human":"2014-Mar-27","y":2014,"m":3},{"category":0,"platform":37,"date":1395878400000,"region":2,"human":"2014-Mar-27","y":2014,"m":3}],"screenshots":[{"url":"\/\/images.igdb.com\/igdb\/image\/upload\/t_thumb\/grwdy4xosmps6gh5zjsu.jpg","cloudinary_id":"grwdy4xosmps6gh5zjsu","width":400,"height":240},{"url":"\/\/images.igdb.com\/igdb\/image\/upload\/t_thumb\/skx0pbiigjtkfxlhkpz5.jpg","cloudinary_id":"skx0pbiigjtkfxlhkpz5","width":400,"height":240},{"url":"\/\/images.igdb.com\/igdb\/image\/upload\/t_thumb\/gnm6ip7pklcrdalnzbeu.jpg","cloudinary_id":"gnm6ip7pklcrdalnzbeu","width":400,"height":240},{"url":"\/\/images.igdb.com\/igdb\/image\/upload\/t_thumb\/voiqvjllvlkkt8tiknqt.jpg","cloudinary_id":"voiqvjllvlkkt8tiknqt","width":400,"height":240},{"url":"\/\/images.igdb.com\/igdb\/image\/upload\/t_thumb\/y7vyl2moosvzsvnq5thi.jpg","cloudinary_id":"y7vyl2moosvzsvnq5thi","width":400,"height":240},{"url":"\/\/images.igdb.com\/igdb\/image\/upload\/t_thumb\/o2go6cnhbgqptoqu5dov.jpg","cloudinary_id":"o2go6cnhbgqptoqu5dov","width":400,"height":240}],"cover":{"url":"\/\/images.igdb.com\/igdb\/image\/upload\/t_thumb\/lq6fc752owvoceutnrxs.jpg","cloudinary_id":"lq6fc752owvoceutnrxs","width":568,"height":461}}