{"id":64015,"name":"WildMan","slug":"wildman","url":"https:\/\/www.igdb.com\/games\/wildman","created_at":1505135798463,"updated_at":1534859759544,"summary":"WildMan is a Kickstarter-funded combination of a RPG and a RTS from Gas Powered Games.","hypes":1,"popularity":1.333333333333333,"games":[55029,28794,44102,6414,2015,9789,34269,6985,8773,30229],"tags":[268435467,268435471,536871338,536871938,536872383,536875869],"category":0,"keywords":[426,1026,1471,4957],"genres":[11,15],"cover":{"url":"\/\/images.igdb.com\/igdb\/image\/upload\/t_thumb\/cehykbtwqmoymh75q9ag.jpg","cloudinary_id":"cehykbtwqmoymh75q9ag","width":1280,"height":720}}