{"id":28046,"name":"Lil Tanks","slug":"lil-tanks","url":"https:\/\/www.igdb.com\/games\/lil-tanks","created_at":1491242101803,"updated_at":1523387061087,"summary":"Lil Tanks is an action-packed, side-scrolling shooter that puts you in control of a prototype tank -- defending humanity from the alien scourge known as The Cuur. As Earth's last hope, you must upgrade your tank with unique power-ups and blast the aliens back to where they came from! Level up by destroying The Cuur and earn powerful permanent upgrades. Unlock multiple tanks by completing objectives and finishing the campaign. The survival of the human race rests in your hands!","storyline":"The Cuur have invaded Earth and started terraforming the planet \u2013 reshaping the terrain and tinkering with the atmosphere. In a last-ditch effort, Humanity\u2019s greatest minds have come together to create a prototype vehicle program \u2013 code-named \u201cLil Tanks.\u201d","popularity":1.333333333333333,"games":[28029,10039,32902,25311,64204,68287,34919,76229,27314,16468],"tags":[1,18,268435461,268435488,268435489,1073741828,1073741827],"developers":[12427],"publishers":[12427],"game_engines":[79],"category":0,"player_perspectives":[3,4],"game_modes":[1,3],"themes":[1,18],"genres":[5,32,33],"first_release_date":1491264000000,"platforms":[6,14,3],"release_dates":[{"category":0,"platform":3,"date":1491264000000,"region":8,"human":"2017-Apr-04","y":2017,"m":4},{"category":0,"platform":14,"date":1491264000000,"region":8,"human":"2017-Apr-04","y":2017,"m":4},{"category":0,"platform":6,"date":1491264000000,"region":8,"human":"2017-Apr-04","y":2017,"m":4}],"screenshots":[{"url":"\/\/images.igdb.com\/igdb\/image\/upload\/t_thumb\/lakghcsitsub6zatsng1.jpg","cloudinary_id":"lakghcsitsub6zatsng1","width":718,"height":478},{"url":"\/\/images.igdb.com\/igdb\/image\/upload\/t_thumb\/qif1f8ctamb81023hyo2.jpg","cloudinary_id":"qif1f8ctamb81023hyo2","width":718,"height":478},{"url":"\/\/images.igdb.com\/igdb\/image\/upload\/t_thumb\/xn0aeoouch9rpefjfzpc.jpg","cloudinary_id":"xn0aeoouch9rpefjfzpc","width":718,"height":478},{"url":"\/\/images.igdb.com\/igdb\/image\/upload\/t_thumb\/svh9ycp5wuvb8n099ajq.jpg","cloudinary_id":"svh9ycp5wuvb8n099ajq","width":718,"height":478},{"url":"\/\/images.igdb.com\/igdb\/image\/upload\/t_thumb\/qg39xbzrgzef85kkwqmp.jpg","cloudinary_id":"qg39xbzrgzef85kkwqmp","width":718,"height":478}],"videos":[{"name":"Trailer","video_id":"HoDYA7EIdec"}],"cover":{"url":"\/\/images.igdb.com\/igdb\/image\/upload\/t_thumb\/w3rz9b4okjhf7xjvgh04.jpg","cloudinary_id":"w3rz9b4okjhf7xjvgh04","width":1920,"height":1080},"websites":[{"category":13,"url":"https:\/\/store.steampowered.com\/app\/495820"},{"category":9,"url":"https:\/\/www.youtube.com\/channel\/UCNGfmpj7Vat-TerJJeA9-Pw"},{"category":5,"url":"https:\/\/twitter.com\/@leadmoneygames"},{"category":4,"url":"https:\/\/www.facebook.com\/leadmoneygames"},{"category":1,"url":"http:\/\/liltanksgame.com"}],"external":{"steam":"495820"},"multiplayer_modes":[{"platform":6,"offlinecoop":true,"onlinecoop":false,"lancoop":false,"campaigncoop":true,"splitscreenonline":false,"splitscreen":false,"dropin":false,"offlinecoopmax":2,"onlinecoopmax":0,"onlinemax":0,"offlinemax":0}]}