{"id":49754,"name":"Kawaii Koinu Mini: Wanko to Asobou!! Kogatainu","slug":"kawaii-koinu-mini-wanko-to-asobou-kogatainu","url":"https:\/\/www.igdb.com\/games\/kawaii-koinu-mini-wanko-to-asobou-kogatainu","created_at":1500025085609,"updated_at":1500377517410,"summary":"Nakayoshi Pet Advance Series 4: Kawaii Koinu Mini - Wanko to Asobou!! Kogatainu is a Strategy game, published by MTO, which was released in Japan in 2003.","popularity":1.333333333333333,"category":0,"genres":[15],"first_release_date":1060560000000,"platforms":[24],"release_dates":[{"category":0,"platform":24,"date":1060560000000,"region":8,"human":"2003-Aug-11","y":2003,"m":8}]}