{"id":22188,"name":"Buddha Finger","slug":"buddha-finger","url":"https:\/\/www.igdb.com\/games\/buddha-finger","created_at":1470230272228,"updated_at":1516755530546,"summary":"Game inspired by Elite Beat Agents and martial arts flicks.","popularity":1.333333333333333,"games":[76110,19376,19290,19934,52530,11997,23330,54524,41828,28154],"tags":[536870973,536872897,536875046],"category":0,"keywords":[61,1985,4134],"first_release_date":1351382400000,"platforms":[34,39],"release_dates":[{"category":0,"platform":34,"date":1377129600000,"region":2,"human":"2013-Aug-22","y":2013,"m":8},{"category":0,"platform":39,"date":1351382400000,"region":2,"human":"2012-Oct-28","y":2012,"m":10}],"cover":{"url":"\/\/images.igdb.com\/igdb\/image\/upload\/t_thumb\/kybqplyexpmypxt94yis.jpg","cloudinary_id":"kybqplyexpmypxt94yis","width":137,"height":153}}