{"id":73500,"name":"The Royal Game of Ur","slug":"the-royal-game-of-ur","url":"https:\/\/www.igdb.com\/games\/the-royal-game-of-ur","created_at":1507203492449,"updated_at":1547109634874,"summary":"The Royal Game of Ur is an ancient racing game where players try to get all of their tokens across the board first. 3000 years ago this was one of the most popular board games in the world. Play it yourself to find out why!","popularity":1,"games":[77597,33552,55036,17613,32510,30457,9472,29173,36553,55590],"tags":[268435471,536874694],"category":0,"game_modes":[1,2],"keywords":[3782],"genres":[15],"screenshots":[{"url":"\/\/images.igdb.com\/igdb\/image\/upload\/t_thumb\/sc5ta7.jpg","cloudinary_id":"sc5ta7","width":1920,"height":1080},{"url":"\/\/images.igdb.com\/igdb\/image\/upload\/t_thumb\/sc5ta6.jpg","cloudinary_id":"sc5ta6","width":1920,"height":1080},{"url":"\/\/images.igdb.com\/igdb\/image\/upload\/t_thumb\/sc5ta5.jpg","cloudinary_id":"sc5ta5","width":1920,"height":1080},{"url":"\/\/images.igdb.com\/igdb\/image\/upload\/t_thumb\/sc5ta4.jpg","cloudinary_id":"sc5ta4","width":1920,"height":1080},{"url":"\/\/images.igdb.com\/igdb\/image\/upload\/t_thumb\/sc5ta3.jpg","cloudinary_id":"sc5ta3","width":1920,"height":1080}],"websites":[{"category":13,"url":"https:\/\/store.steampowered.com\/app\/955470"}],"external":{"steam":"955470"}}