{"id":58703,"name":"Beautiful Dreamer","slug":"beautiful-dreamer","url":"https:\/\/www.igdb.com\/games\/beautiful-dreamer","created_at":1504728484375,"updated_at":1516638132930,"summary":"A piece of Interactive Fiction created with Twine by S. Woodson.","popularity":1,"games":[80461,76010,73834,72640,72537,72034,70803,60718,60186,60185],"tags":[536871208,536873308,536875172],"category":0,"keywords":[296,2396,4260],"cover":{"url":"\/\/images.igdb.com\/igdb\/image\/upload\/t_thumb\/cb3cbavdahyfsg2lbutg.jpg","cloudinary_id":"cb3cbavdahyfsg2lbutg","width":315,"height":250}}