{"id":57941,"name":"Yuusha-Ou GaoGaiGar: Blockaded Numbers","slug":"yuusha-ou-gaogaigar-blockaded-numbers","url":"https:\/\/www.igdb.com\/games\/yuusha-ou-gaogaigar-blockaded-numbers","created_at":1504702663917,"updated_at":1516621354347,"summary":"An adventure game containing two original stories presented as TV episodes set within the GaoGaiGar universe.","popularity":1.333333333333333,"games":[55803,29730,13189,25222,41895,22482,70861,22425,61267,11296],"tags":[268435487,536870990,536871939],"category":0,"keywords":[78,1027],"genres":[31],"cover":{"url":"\/\/images.igdb.com\/igdb\/image\/upload\/t_thumb\/bhmt0gary76v8hxs4s41.jpg","cloudinary_id":"bhmt0gary76v8hxs4s41","width":1399,"height":1385}}