{"id":10407,"name":"Helicopter Simulator 2014: Search and Rescue","slug":"helicopter-simulator-2014-search-and-rescue","url":"https:\/\/www.igdb.com\/games\/helicopter-simulator-2014-search-and-rescue","created_at":1431951699593,"updated_at":1523262807925,"summary":"Become an emergency pilot and test your skills to their limits, as you sit in the cockpit of an emergency helicopter, across more than 40 challenging missions. Choose from 8 models of 'copter, each varying in size, ability and specs.\n\nFighting forest fires, communication failures, and conducting perilous search & rescue missions are just the start... you'll face many more natural disasters throughout your missions.","rating":40,"popularity":1,"total_rating":40,"total_rating_count":0,"rating_count":0,"games":[44242,19290,18623,19934,22470,29173,26145,22425,55689,54524],"tags":[32,268435469,536872060,536875046,536876726],"category":0,"game_modes":[1],"keywords":[1148,4134,5814],"themes":[32],"genres":[13],"first_release_date":1393545600000,"platforms":[6],"release_dates":[{"category":0,"platform":6,"date":1393545600000,"region":8,"human":"2014-Feb-28","y":2014,"m":2}],"screenshots":[{"url":"\/\/images.igdb.com\/igdb\/image\/upload\/t_thumb\/ex1icwgjlhv5s2bmf3rx.jpg","cloudinary_id":"ex1icwgjlhv5s2bmf3rx","width":1280,"height":720},{"url":"\/\/images.igdb.com\/igdb\/image\/upload\/t_thumb\/br8taxmnspfgmkcfnsat.jpg","cloudinary_id":"br8taxmnspfgmkcfnsat","width":1600,"height":900},{"url":"\/\/images.igdb.com\/igdb\/image\/upload\/t_thumb\/d8lc8l7qof3cu5zbzz4h.jpg","cloudinary_id":"d8lc8l7qof3cu5zbzz4h","width":1280,"height":720},{"url":"\/\/images.igdb.com\/igdb\/image\/upload\/t_thumb\/ajeyuevehcsjnqjl8pon.jpg","cloudinary_id":"ajeyuevehcsjnqjl8pon","width":1600,"height":900},{"url":"\/\/images.igdb.com\/igdb\/image\/upload\/t_thumb\/jlwthg7xljwa9ikmktul.jpg","cloudinary_id":"jlwthg7xljwa9ikmktul","width":1600,"height":900}],"videos":[{"name":"Gameplay video","video_id":"ccxKo6-qt5c"}],"cover":{"url":"\/\/images.igdb.com\/igdb\/image\/upload\/t_thumb\/qjtvhea5v5vog0cz6bfr.jpg","cloudinary_id":"qjtvhea5v5vog0cz6bfr","width":512,"height":512},"websites":[{"category":1,"url":"http:\/\/www.hssr.playway.com\/"},{"category":13,"url":"https:\/\/store.steampowered.com\/app\/266290"}],"external":{"steam":"266290"}}