{"attributes":{"badge-info":{"non-plus-user":null,"plus-user":null},"cero-z-status":{"is-allowed-in-cart":false,"is-on":false},"content-rating":{"content-descriptors":[{"description":"Violence","name":"Violence","url":null},{"description":"Blood","name":"Blood","url":null},{"description":"Partial Nudity","name":"Partial Nudity","url":null},{"description":"Language","name":"Language","url":null},{"description":"Suggestive Themes","name":"Suggestive Themes","url":null}],"contentInteractiveElement":[],"rating-system":"ESRB","url":"https:\/\/cdn-a.sonyentertainmentnetwork.com\/grc\/images\/ratings\/hd\/esrb\/m.png"},"content-type":"1","default-sku-id":"UP9000-NPUD21621_00-0000000000000000-UG01","dob-required":true,"file-size":{"unit":"GB","value":4.31},"game-content-type":"PS2\u2122 Classic","genres":["Role-Playing Games (RPG)"],"is-igc-upsell":false,"is-multiplayer-upsell":false,"kamaji-relationship":"extras","legal-text":"","long-description":"Juggle high school social life and dungeon crawling in this innovative RPG where you fight Shadows with your inner power, known as a Persona.<br><br>Download Shin Megami Tensei\u00ae: Persona\u00ae 3 FES today!<br><br>\u00a9Index Corporation 2006-2008. Produced by ATLUS. SMT, SHIN MEGAMI TENSEI, and PERSONA are registered trademarks of Index Digital Media, Inc.<br><br>This title has been converted from the original PlayStation\u00ae2 version to the PS3\u2122 system. Consequently, there may be times where the title plays differently from the PlayStation\u00ae2 version, or where some features may not function properly. This version does not support PlayStation\u00ae2 peripherals, therefore functionalities such as multiplayer, versus, and co-op modes may not be available.<br><br>Please Re-enter Text Here<br><br>  Software subject to license (us.playstation.com\/softwarelicense).  Online activity subject to Terms of Services and User Agreement (www.playstationnetwork.com\/terms-of-service).","macross-brain-context":"game","media-list":{"preview":[],"promo":{"images":[{"url":"https:\/\/nsx.np.dl.playstation.net\/nsx\/material\/6\/636f1f48dc544440c581eff7a791c0451952224f-255592.png"},{"url":"https:\/\/nsx.np.dl.playstation.net\/nsx\/material\/b\/bf4eaf5c309669457c85412477a3b0a96c90a079-255591.png"},{"url":"https:\/\/nsx.np.dl.playstation.net\/nsx\/material\/7\/7b56388a2ec642c37b1d3d876f480fe4215d62b4-255590.png"},{"url":"https:\/\/nsx.np.dl.playstation.net\/nsx\/material\/4\/40a4bbad6c87f8bfc5ac34229669e1fb83e5bd6c-255589.png"},{"url":"https:\/\/nsx.np.dl.playstation.net\/nsx\/material\/8\/8b8490392860477c1747a8d1ba94524404acd9f1-255588.png"},{"url":"https:\/\/nsx.np.dl.playstation.net\/nsx\/material\/3\/3d995038acfa2db8abaa5e222c04bd819a4b2113-255587.png"},{"url":"https:\/\/nsx.np.dl.playstation.net\/nsx\/material\/b\/be3aa8e6db5c4670ef39cffae7a8c8aefdd2b27b-255586.png"},{"url":"https:\/\/nsx.np.dl.playstation.net\/nsx\/material\/f\/f2753aa26078291e68dd381875fcfdaf687e1425-255585.png"},{"url":"https:\/\/nsx.np.dl.playstation.net\/nsx\/material\/d\/d79c54996494f1e1930a79a9732177e47a2c9e61-255584.png"},{"url":"https:\/\/nsx.np.dl.playstation.net\/nsx\/material\/0\/0b9e8833d1b738dc749038713bc9292123570ce0-255583.png"}],"videos":[]},"screenshots":[]},"name":"Shin Megami Tensei\u00ae: Persona\u00ae 3 FES (PS2 Classic)","nsx-confirm-message":"","parent":null,"platforms":["PS3"],"plus-reward-description":null,"primary-classification":"DOWNLOADABLE_GAME","provider-name":"Sony Interactive Entertainment","ps-camera-compatibility":"incompatible","ps-move-compatibility":"incompatible","ps-vr-compatibility":"incompatible","release-date":"2012-04-10T00:00:00Z","secondary-classification":"PS2_CLASSIC","skus":[{"entitlements":[{"duration":0,"exp-after-first-use":0}],"id":"UP9000-NPUD21621_00-0000000000000000-UG01","is-preorder":false,"multibuy":null,"name":"Full Game","playability-date":"","plus-reward-description":null,"prices":{"non-plus-user":{"actual-price":{"display":"$9.99","value":999},"availability":{"end-date":null,"start-date":null},"discount-percentage":0,"is-plus":false,"strikethrough-price":null,"upsell-price":null},"plus-user":{"actual-price":{"display":"$9.99","value":999},"availability":{"end-date":null,"start-date":null},"discount-percentage":0,"is-plus":false,"strikethrough-price":null,"upsell-price":null}}}],"star-rating":{"score":4.93,"total":7659},"subtitle-language-codes":[],"tertiary-classification":"NA","thumbnail-url-base":"https:\/\/store.playstation.com\/store\/api\/chihiro\/00_09_000\/container\/US\/en\/999\/UP9000-NPUD21621_00-0000000000000000\/1527148947000\/image","top-category":"downloadable_game","upsell-info":null,"voice-language-codes":[]},"id":"UP9000-NPUD21621_00-0000000000000000","relationships":{"children":{"data":[]},"legacy-skus":{"data":[{"id":"UP9000-NPUD21621_00-0000000000000000-UG01","type":"legacy-sku"}]}},"type":"game"}