{"id":68049,"name":"The Maiden Rape Assault: Violent Semen Inferno","slug":"the-maiden-rape-assault-violent-semen-inferno","url":"https:\/\/www.igdb.com\/games\/the-maiden-rape-assault-violent-semen-inferno","created_at":1505481181546,"updated_at":1542378132325,"summary":"A rape-themed pornographic game in which the player character performs actions such as forcing himself sexually on a stranger on her wedding day.","hypes":1,"popularity":289.3333333333333,"games":[22482,22472,28465,22406,41895,17906,22471,22470,76397,22425],"tags":[42,268435469,536870990,536871255,536872060,536872873,536874498,536878208],"category":0,"keywords":[78,343,1148,1961,3586,7296],"themes":[42],"genres":[13],"cover":{"url":"\/\/images.igdb.com\/igdb\/image\/upload\/t_thumb\/h2wsrehba34xjsek1rl7.jpg","cloudinary_id":"h2wsrehba34xjsek1rl7","width":800,"height":600}}