{"id":53163,"name":"Sl\u00e1ine, the Celtic Barbarian","slug":"slaine-the-celtic-barbarian","url":"https:\/\/www.igdb.com\/games\/slaine-the-celtic-barbarian","created_at":1501542414740,"updated_at":1515608184043,"popularity":1.333333333333333,"games":[19289,13189,36792,25222,236,41895,26163,22425,55803,37088],"tags":[17,268435487,536871905,536871939,536873303,536880564,1073741826,1073741829],"developers":[1182],"publishers":[12661],"category":0,"player_perspectives":[2,5],"game_modes":[1],"keywords":[993,1027,2391,9652],"themes":[17],"genres":[31],"first_release_date":567907200000,"platforms":[15,26,25],"release_dates":[{"category":2,"platform":26,"date":567907200000,"region":1,"human":"1987","y":1987,"m":12},{"category":2,"platform":15,"date":567907200000,"region":1,"human":"1987","y":1987,"m":12},{"category":2,"platform":25,"date":567907200000,"region":1,"human":"1987","y":1987,"m":12}],"alternative_names":[{"name":"Slaine Fromn 2000 AD"}],"cover":{"url":"\/\/images.igdb.com\/igdb\/image\/upload\/t_thumb\/qib0uhxshfgmr0zpu6lz.jpg","cloudinary_id":"qib0uhxshfgmr0zpu6lz","width":1000,"height":1405}}