{"id":57363,"name":"Best Fiends Forever","slug":"best-fiends-forever","url":"https:\/\/www.igdb.com\/games\/best-fiends-forever","created_at":1504605105080,"updated_at":1536891456605,"summary":"Get ready for the very big adventure with very small heroes! The sequel to the award-sometimes-winning-and-if-not-we're-just-happy-to-be-nominated Best Fiends! But it's nothing like that game! Except that it's got the same characters, and you're still beating up slugs. But it's a clicker adventure, which is different, and we think a lot of fun!","storyline":"Taken from the Google Play description \n \nStory: The Fiends finally made it to Mount Boom, only to be defeated and imprisoned in very similar boxes. Now it's time for YOU to turn the tables! Round up the old gang, level them up and defeat wave after wave of slugs as you make your way to the elusive villain behind the Slug Invasion! \n \nWith the help of the Fiends, and the awesome reckoning power of Mount Boom, and the magical souvenirs that boost your strength, and whatever new stuff we come up with down the line, you'll save the world in no time. And then realize there's more to this game than even that! And then hate us for making a game you can't stop playing! \n \nAnd there's no energy mechanics, you can play it whenever you want, for as long as you want! Which is good, since you've obviously got some time on your hands if you bothered to read this far through the description. So get it already. Best Fiends FOREVER!","collection":3822,"franchise":1326,"franchises":[1326],"hypes":1,"popularity":1.666666666666667,"games":[109581,25877,26163,29032,22917,113360,28070,107044,47823,103303],"tags":[17,35,268435488,536873430,536874191,536875405,536894163,1073741827],"developers":[16380],"category":0,"player_perspectives":[3],"game_modes":[1],"keywords":[2518,3279,4493,23251],"themes":[17,35],"genres":[32],"first_release_date":1449792000000,"platforms":[34,39],"release_dates":[{"category":0,"platform":34,"date":1449792000000,"region":8,"human":"2015-Dec-11","y":2015,"m":12},{"category":0,"platform":39,"date":1449792000000,"region":8,"human":"2015-Dec-11","y":2015,"m":12}],"videos":[{"name":"Gameplay video","video_id":"8y4SowgPlxg"},{"name":"Trailer","video_id":"wZj5J-QINJE"},{"name":"Trailer","video_id":"qHblGUsc6RM"}],"cover":{"url":"\/\/images.igdb.com\/igdb\/image\/upload\/t_thumb\/qe5b3r07ianwmxwyse8j.jpg","cloudinary_id":"qe5b3r07ianwmxwyse8j","width":930,"height":522},"esrb":{"rating":3},"websites":[{"category":14,"url":"https:\/\/www.reddit.com\/r\/BestFiendsForever"},{"category":12,"url":"https:\/\/play.google.com\/store\/apps\/details?id=com.Seriously.Forever&hl=en_US"},{"category":10,"url":"https:\/\/itunes.apple.com\/NZ\/app\/id1059405547?mt=8"},{"category":9,"url":"https:\/\/www.youtube.com\/user\/SeriouslyHQ"},{"category":8,"url":"https:\/\/www.instagram.com\/bestfiends"},{"category":5,"url":"https:\/\/twitter.com\/bestfiends"},{"category":4,"url":"https:\/\/www.facebook.com\/bestfiends"},{"category":2,"url":"http:\/\/best-fiends-forever.wikia.com\/wiki\/Main_Page"},{"category":1,"url":"https:\/\/bestfiends.com\/games\/best-fiends-forever\/"}]}