{"id":61153,"name":"Bit Bit Blocks","slug":"bit-bit-blocks","url":"https:\/\/www.igdb.com\/games\/bit-bit-blocks","created_at":1504871586103,"updated_at":1516691897835,"summary":"Bit Bit Blocks is a 2-player competitive puzzle game for iOS and Android.","popularity":1.333333333333333,"games":[25222,54678,19376,60044,20329,14047,26223,19290,19934,63117],"tags":[268435465,536871029,536873787,536875046,536876228],"category":0,"keywords":[117,2875,4134,5316],"genres":[9],"cover":{"url":"\/\/images.igdb.com\/igdb\/image\/upload\/t_thumb\/gdjojeebc2tnkzzpmsfx.jpg","cloudinary_id":"gdjojeebc2tnkzzpmsfx","width":299,"height":219}}