{"id":42932,"name":"Monster Jam: Crush It!","slug":"monster-jam-crush-it","url":"https:\/\/www.igdb.com\/games\/monster-jam-crush-it","created_at":1499084207897,"updated_at":1534365933355,"summary":"Monster Jam: Crush It! features a massive variety of game modes with online and offline leaderboards and a colossal emphasis on stadium events, big stunts and destruction. The game offers classic, competitive stadium racing and freestyle, and gives gamers the ability to perform gravity-defying stunts for huge rewards throughout over 96 different challenges in survivor, stunt and hill climb race modes. Out-of-stadium experiences include action in polar, desert, harbor and forest environments, powered by Unreal Engine 4, with main music produced by Somatone Interactive. There are 24 fully licensed and playable trucks to choose from in Monster Jam: Crush It!, including real-life legends like Grave Digger\u00ae, Monster Mutt\u00ae, Blue Thunder\u00ae and ZombieTM. The game captures a cinematic, live-event feel across six genuine Monster Jam arenas.","collection":3363,"rating":50,"popularity":1.666666666666667,"total_rating":50,"total_rating_count":0,"rating_count":0,"games":[76566,27378,101439,23304,89444,103218,3772,55092,103316,19150],"tags":[1,268435466,268435470,536871537,536872736,536873207,536874657,536875046,536875069,536881628,536889361,536889362,536889363],"developers":[8385],"publishers":[2329],"category":0,"keywords":[625,1824,2295,3745,4134,4157,10716,18449,18450,18451],"themes":[1],"genres":[10,14],"first_release_date":1477353600000,"platforms":[48,49,130],"release_dates":[{"category":0,"platform":49,"date":1477353600000,"region":2,"human":"2016-Oct-25","y":2016,"m":10},{"category":0,"platform":48,"date":1477353600000,"region":2,"human":"2016-Oct-25","y":2016,"m":10},{"category":0,"platform":130,"date":1509408000000,"region":2,"human":"2017-Oct-31","y":2017,"m":10}],"screenshots":[{"url":"\/\/images.igdb.com\/igdb\/image\/upload\/t_thumb\/uh0u1p36mlclnhiwlr4y.jpg","cloudinary_id":"uh0u1p36mlclnhiwlr4y","width":1920,"height":1080},{"url":"\/\/images.igdb.com\/igdb\/image\/upload\/t_thumb\/n3qw33vabpqtvwvno1bz.jpg","cloudinary_id":"n3qw33vabpqtvwvno1bz","width":1920,"height":1080},{"url":"\/\/images.igdb.com\/igdb\/image\/upload\/t_thumb\/sxnuzxzjz9gyxrf42dyp.jpg","cloudinary_id":"sxnuzxzjz9gyxrf42dyp","width":1920,"height":1080},{"url":"\/\/images.igdb.com\/igdb\/image\/upload\/t_thumb\/stq0tylzsrmcnuc1wwvb.jpg","cloudinary_id":"stq0tylzsrmcnuc1wwvb","width":1920,"height":1080},{"url":"\/\/images.igdb.com\/igdb\/image\/upload\/t_thumb\/j59smiem06rlvlmzkwhe.jpg","cloudinary_id":"j59smiem06rlvlmzkwhe","width":1920,"height":1080},{"url":"\/\/images.igdb.com\/igdb\/image\/upload\/t_thumb\/a5bnir5hfcgmg86ra7ix.jpg","cloudinary_id":"a5bnir5hfcgmg86ra7ix","width":1920,"height":1080},{"url":"\/\/images.igdb.com\/igdb\/image\/upload\/t_thumb\/npktum5wnkjjidqeobcp.jpg","cloudinary_id":"npktum5wnkjjidqeobcp","width":1920,"height":1080},{"url":"\/\/images.igdb.com\/igdb\/image\/upload\/t_thumb\/lkqtck6uf88ukiap9dei.jpg","cloudinary_id":"lkqtck6uf88ukiap9dei","width":1920,"height":1080},{"url":"\/\/images.igdb.com\/igdb\/image\/upload\/t_thumb\/qmovsb85brcmm7owewxw.jpg","cloudinary_id":"qmovsb85brcmm7owewxw","width":1920,"height":1080},{"url":"\/\/images.igdb.com\/igdb\/image\/upload\/t_thumb\/rchgjmukw0kfhmto8ktg.jpg","cloudinary_id":"rchgjmukw0kfhmto8ktg","width":1920,"height":1080},{"url":"\/\/images.igdb.com\/igdb\/image\/upload\/t_thumb\/eo9lnyfhmnontmk6tehy.jpg","cloudinary_id":"eo9lnyfhmnontmk6tehy","width":1920,"height":1080}],"cover":{"url":"\/\/images.igdb.com\/igdb\/image\/upload\/t_thumb\/ktp260wcqviqkq1xaxym.jpg","cloudinary_id":"ktp260wcqviqkq1xaxym","width":720,"height":1080},"esrb":{"rating":3}}