{"id":113567,"name":"Xen the Alien","slug":"xen-the-alien","url":"https:\/\/www.igdb.com\/games\/xen-the-alien","created_at":1546884887422,"updated_at":1546885211807,"summary":"Xen the Alien is a third-person, action-adventure and puzzle game that follows the exploits of an Alien scout named Xen desperately trying to find his way back home after being marooned on the Alien planet Naytonia. Xen must traverse the different locations of the planet in search of the missing parts of his Ship as well as contend with a mysterious military presence on the planet using either a lethal or stealthy approach, the choice is yours!","popularity":5,"games":[105269,26298,25311,112657,17130,89550,8367,82117,19128,34823],"tags":[18,268435488,1073741826],"developers":[17228],"publishers":[17228],"category":0,"player_perspectives":[2],"game_modes":[1],"themes":[18],"genres":[32],"first_release_date":1577750400000,"platforms":[34,6],"release_dates":[{"category":7,"platform":34,"human":"TBD"},{"category":2,"platform":6,"date":1577750400000,"human":"2019","y":2019,"m":12}],"screenshots":[{"url":"\/\/images.igdb.com\/igdb\/image\/upload\/t_thumb\/sc5sc5.jpg","cloudinary_id":"sc5sc5","width":800,"height":450},{"url":"\/\/images.igdb.com\/igdb\/image\/upload\/t_thumb\/sc5sc4.jpg","cloudinary_id":"sc5sc4","width":800,"height":450},{"url":"\/\/images.igdb.com\/igdb\/image\/upload\/t_thumb\/sc5sc3.jpg","cloudinary_id":"sc5sc3","width":800,"height":450},{"url":"\/\/images.igdb.com\/igdb\/image\/upload\/t_thumb\/sc5sc2.jpg","cloudinary_id":"sc5sc2","width":800,"height":450},{"url":"\/\/images.igdb.com\/igdb\/image\/upload\/t_thumb\/sc5sc1.jpg","cloudinary_id":"sc5sc1","width":800,"height":450}],"videos":[{"name":"Trailer","video_id":"RqMqWR791zo"},{"name":"Trailer","video_id":"w_a3S2U1pyE"}],"cover":{"url":"\/\/images.igdb.com\/igdb\/image\/upload\/t_thumb\/co1ih5.jpg","cloudinary_id":"co1ih5","width":270,"height":360},"websites":[{"category":15,"url":"https:\/\/hexgear.itch.io\/xen-the-alien-full-game"},{"category":12,"url":"https:\/\/play.google.com\/store\/apps\/details?id=com.hexgear.xta.apk"},{"category":9,"url":"https:\/\/www.youtube.com\/channel\/UCIYfd7dRIXZ7TNbUXxMu0EA"},{"category":5,"url":"https:\/\/twitter.com\/xenthealien"},{"category":1,"url":"http:\/\/xenthealien.com\/demo_page.php"}]}