{"attributes":{"badge-info":{"non-plus-user":null,"plus-user":null},"cero-z-status":{"is-allowed-in-cart":false,"is-on":false},"content-rating":{"content-descriptors":[{"description":"Mild Cartoon Violence","name":"Mild Cartoon Violence","url":null},{"description":"Comic Mischief","name":"Comic Mischief","url":null}],"contentInteractiveElement":[],"rating-system":"ESRB","url":"https:\/\/cdn-a.sonyentertainmentnetwork.com\/grc\/images\/ratings\/hd\/esrb\/e-e10.png"},"content-type":"1","default-sku-id":"UP4069-NPUZ00289_00-101IN1ANDFADINGS-UB02","dob-required":false,"file-size":{"unit":"MB","value":710.7},"game-content-type":"Bundle","genres":["Action","Puzzle","Racing","Simulation","Arcade"],"is-igc-upsell":false,"is-multiplayer-upsell":false,"kamaji-relationship":"bundles","legal-text":"","long-description":"2 great games in one pack!\r\n<br><br>\r\nFading Shadows: Take control of the beam of light to guide the orb through an intriguing world of danger and adventure. It won't be easy, as evil enemies will try to stop you at all costs... Avoid the traps whilst solving puzzles and riddles designed to slow you down. Overcome the obstacles in your way, and change the orb's form into wood to conquer water, or even metal when hardness is needed.\r\n<br><br>\r\n101-in-1 Megamix: Welcome to the world of 101-in-1 Megamix  a monumental collection of games for the PSP\u00ae (PlayStation\u00aePortable) system  boasting a unique visual style, a wide variety of unlockable games and prizes, and superb multiplayer action.101 different games take you from the depths of the ocean to the Wild West... From the Stone Age to space racing...  \r\n<br><br>\r\n\u00a9 Nordcurrent\r\n<br><br>\r\nPurchase or use of this item is subject to the PlayStation\u00aeNetwork Terms of Service and User Agreement. This item has been sublicensed to you by Sony Computer Entertainment America.\r\n","macross-brain-context":"game","media-list":{"preview":[],"promo":{"images":[],"videos":[{"url":"https:\/\/nsx.np.dl.playstation.net\/nsx\/material\/b\/ba5ea4742123a3b022e6c61123fb229ebeed1353-180481.mp4?country=US"}]},"screenshots":[]},"name":"101-in-1 Megamix+Fading Shadows Bundle","nsx-confirm-message":"","parent":null,"platforms":["PSP","PS Vita"],"plus-reward-description":null,"primary-classification":"DOWNLOADABLE_GAME","provider-name":"Nordcurrent UAB","ps-camera-compatibility":"incompatible","ps-move-compatibility":"incompatible","ps-vr-compatibility":"incompatible","release-date":"2011-12-20T00:00:00Z","secondary-classification":"GAME","skus":[{"entitlements":[{"duration":0,"exp-after-first-use":0},{"duration":0,"exp-after-first-use":0}],"id":"UP4069-NPUZ00289_00-101IN1ANDFADINGS-UB02","is-preorder":false,"multibuy":null,"name":"712 MB Required","playability-date":"","plus-reward-description":null,"prices":{"non-plus-user":{"actual-price":{"display":"$10.99","value":1099},"availability":{"end-date":null,"start-date":null},"discount-percentage":0,"is-plus":false,"strikethrough-price":null,"upsell-price":null},"plus-user":{"actual-price":{"display":"$10.99","value":1099},"availability":{"end-date":null,"start-date":null},"discount-percentage":0,"is-plus":false,"strikethrough-price":null,"upsell-price":null}}}],"star-rating":{"score":2.4,"total":5},"subtitle-language-codes":[],"tertiary-classification":"BUNDLE","thumbnail-url-base":"https:\/\/store.playstation.com\/store\/api\/chihiro\/00_09_000\/container\/US\/en\/999\/UP4069-NPUZ00289_00-101IN1ANDFADINGS\/1520482741000\/image","top-category":"downloadable_game","upsell-info":null,"voice-language-codes":[]},"id":"UP4069-NPUZ00289_00-101IN1ANDFADINGS","relationships":{"children":{"data":[]},"legacy-skus":{"data":[{"id":"UP4069-NPUZ00289_00-101IN1ANDFADINGS-UB02","type":"legacy-sku"}]}},"type":"game"}