{"id":113187,"name":"Eggcellent VR","slug":"eggcellent-vr","url":"https:\/\/www.igdb.com\/games\/eggcellent-vr","created_at":1544166259583,"updated_at":1547460040032,"summary":"Eggcellent VR is a simple arcade game inspired by Mickey Mouse egg catcher on Nintendo Game & Watch. The game is driven by a pure spirit of arcade with every level getting more and more challenging. Despite the inspiration of the game, it has additional gaming modes to keep you entertained.","popularity":1,"games":[86344,74127,82117,26298,99307,107388,10225,27744,34919,110098],"tags":[268435488],"category":0,"game_modes":[1],"genres":[32],"screenshots":[{"url":"\/\/images.igdb.com\/igdb\/image\/upload\/t_thumb\/sc5xjj.jpg","cloudinary_id":"sc5xjj","width":1920,"height":1080},{"url":"\/\/images.igdb.com\/igdb\/image\/upload\/t_thumb\/sc5xji.jpg","cloudinary_id":"sc5xji","width":1920,"height":1079},{"url":"\/\/images.igdb.com\/igdb\/image\/upload\/t_thumb\/sc5xjh.jpg","cloudinary_id":"sc5xjh","width":1920,"height":1080},{"url":"\/\/images.igdb.com\/igdb\/image\/upload\/t_thumb\/sc5xjg.jpg","cloudinary_id":"sc5xjg","width":1920,"height":1080},{"url":"\/\/images.igdb.com\/igdb\/image\/upload\/t_thumb\/sc5xjf.jpg","cloudinary_id":"sc5xjf","width":1920,"height":1080}],"websites":[{"category":1,"url":"http:\/\/www.happybat.com"},{"category":13,"url":"https:\/\/store.steampowered.com\/app\/727840"}],"external":{"steam":"727840"}}