{"id":103369,"name":"Kill la Kill the Game: If","slug":"kill-la-kill-the-game-if","url":"https:\/\/www.igdb.com\/games\/kill-la-kill-the-game-if","created_at":1529050131929,"updated_at":1543107396775,"summary":"A Fighting game based on Kill la Kill being developed by APlus planned for a 2019 release. \n \nMore information to be revealed at Anime Expo 2018, July 5th-8th.","franchise":1285,"franchises":[1285],"hypes":4,"popularity":2.333333333333333,"games":[103288,90101,103282,76428,54775,26879,81249,76736,103269,106987],"tags":[1,17,268435460,536874038,1073741828],"developers":[13112],"publishers":[1218],"category":0,"player_perspectives":[4],"game_modes":[1,2],"keywords":[3126],"themes":[1,17],"genres":[4],"first_release_date":1577750400000,"pulse_count":58,"platforms":[6,48,130],"release_dates":[{"category":2,"platform":130,"date":1577750400000,"human":"2019","y":2019,"m":12},{"category":2,"platform":6,"date":1577750400000,"human":"2019","y":2019,"m":12},{"category":2,"platform":48,"date":1577750400000,"human":"2019","y":2019,"m":12}],"alternative_names":[{"name":"Kill la Kill the Game IF","comment":"Other"},{"name":"\u30ad\u30eb\u30e9\u30ad\u30eb \u30b6\u30fb\u30b2\u30fc\u30e0 -\u7570\u5e03- ","comment":"Japanese title"}],"screenshots":[{"url":"\/\/images.igdb.com\/igdb\/image\/upload\/t_thumb\/uv9ridbrbkptnbnsesvf.jpg","cloudinary_id":"uv9ridbrbkptnbnsesvf","width":600,"height":338},{"url":"\/\/images.igdb.com\/igdb\/image\/upload\/t_thumb\/iztnyreox7ntmfabpsjo.jpg","cloudinary_id":"iztnyreox7ntmfabpsjo","width":600,"height":338},{"url":"\/\/images.igdb.com\/igdb\/image\/upload\/t_thumb\/wezdkrrzgsowgeyqdifn.jpg","cloudinary_id":"wezdkrrzgsowgeyqdifn","width":600,"height":338},{"url":"\/\/images.igdb.com\/igdb\/image\/upload\/t_thumb\/llyjgcjah3zpdyliijut.jpg","cloudinary_id":"llyjgcjah3zpdyliijut","width":600,"height":338}],"videos":[{"name":"Trailer","video_id":"nWeTKT9S0xc"},{"name":"Teaser","video_id":"AO6lopTTqN0"}],"cover":{"url":"\/\/images.igdb.com\/igdb\/image\/upload\/t_thumb\/ulcfmziiqyg3ekow3hpv.jpg","cloudinary_id":"ulcfmziiqyg3ekow3hpv","width":1920,"height":2667}}