{"id":70064,"name":"Poketan","slug":"poketan","url":"https:\/\/www.igdb.com\/games\/poketan","created_at":1506591777096,"updated_at":1515654393813,"summary":"Poketan is an educational Japanese game aimed at teaching English.","popularity":1,"games":[73189,68249,34218,83265,83209,80759,80516,80286,80084,79934],"tags":[34,536871446,536875829],"category":0,"keywords":[534,4917],"themes":[34],"cover":{"url":"\/\/images.igdb.com\/igdb\/image\/upload\/t_thumb\/bjvilwxoygjov0cpenjt.jpg","cloudinary_id":"bjvilwxoygjov0cpenjt","width":472,"height":471}}