{"id":113084,"name":"TurnTack","slug":"turntack","url":"https:\/\/www.igdb.com\/games\/turntack","created_at":1543923211911,"updated_at":1547240246804,"summary":"Monsters destroyed all of the human world. Half-blood girl who is the player in the game goes back to the world that it's yet destroyed. She tries to keep the human world safe but the monsters have been suffering likewise. Therefore she is confused what's right to do because of her half-blood identity.","popularity":1,"games":[26298,110098,28277,55282,81275,36334,37419,68450,75808,18234],"tags":[268435487,268435488],"category":0,"game_modes":[1],"genres":[31,32],"status":4,"screenshots":[{"url":"\/\/images.igdb.com\/igdb\/image\/upload\/t_thumb\/sc5tt9.jpg","cloudinary_id":"sc5tt9","width":1920,"height":1080},{"url":"\/\/images.igdb.com\/igdb\/image\/upload\/t_thumb\/sc5tt8.jpg","cloudinary_id":"sc5tt8","width":1920,"height":1080},{"url":"\/\/images.igdb.com\/igdb\/image\/upload\/t_thumb\/sc5tt7.jpg","cloudinary_id":"sc5tt7","width":1920,"height":1080},{"url":"\/\/images.igdb.com\/igdb\/image\/upload\/t_thumb\/sc5tt6.jpg","cloudinary_id":"sc5tt6","width":1920,"height":1080},{"url":"\/\/images.igdb.com\/igdb\/image\/upload\/t_thumb\/sc5tt5.jpg","cloudinary_id":"sc5tt5","width":1920,"height":1080},{"url":"\/\/images.igdb.com\/igdb\/image\/upload\/t_thumb\/sc5tt4.jpg","cloudinary_id":"sc5tt4","width":1920,"height":1080},{"url":"\/\/images.igdb.com\/igdb\/image\/upload\/t_thumb\/sc5tt3.jpg","cloudinary_id":"sc5tt3","width":1920,"height":1080},{"url":"\/\/images.igdb.com\/igdb\/image\/upload\/t_thumb\/sc5tt2.jpg","cloudinary_id":"sc5tt2","width":1920,"height":1080},{"url":"\/\/images.igdb.com\/igdb\/image\/upload\/t_thumb\/sc5tt1.jpg","cloudinary_id":"sc5tt1","width":1920,"height":1080},{"url":"\/\/images.igdb.com\/igdb\/image\/upload\/t_thumb\/sc5tt0.jpg","cloudinary_id":"sc5tt0","width":1920,"height":1080}],"websites":[{"category":1,"url":"https:\/\/www.facebook.com\/Geuluteogi\/"},{"category":13,"url":"https:\/\/store.steampowered.com\/app\/944710"}],"external":{"steam":"944710"}}