{"attributes":{"badge-info":{"non-plus-user":null,"plus-user":null},"cero-z-status":{"is-allowed-in-cart":false,"is-on":false},"content-rating":{"content-descriptors":[{"description":"Mild Fantasy Violence","name":"Mild Fantasy Violence","url":null}],"contentInteractiveElement":[],"rating-system":"ESRB","url":"https:\/\/cdn-a.sonyentertainmentnetwork.com\/grc\/images\/ratings\/hd\/esrb\/e.png"},"content-type":"1","default-sku-id":"UP4786-CUSA14158_00-CW1PS47890123456-U001","dob-required":false,"file-size":{"unit":"MB","value":118.03},"game-content-type":"PSN Game","genres":[],"is-igc-upsell":false,"is-multiplayer-upsell":false,"kamaji-relationship":"extras","legal-text":"","long-description":"Croc\u00b4s World is a really nice jump'n'run with 60 incredible levels and many challenging enemies!<br><br>It features:<br><br>+ 60 incredible levels (4 for free, others as in-game-purchase)<br>+ Nice graphics<br>+ 4 different themes<br>+ many challenging enemies<br><br>Instructions:<br><br>Jump and run through the levels and dodge all enemies.<br>Collect a helmet to crush stoneblocks.<br>Collect the stonebag to throw stones.<br>If you collect 100 diamonds you\u00b4ll get an extra life!<br><br>1 player<br>DUALSHOCK\u00ae4<br><br>  Software subject to license (us.playstation.com\/softwarelicense). Online features require an account and are subject to terms of service and applicable privacy policy (playstationnetwork.com\/terms-of-service & playstationnetwork.com\/privacy-policy). One-time license fee for play on account\u2019s designated primary PS4\u2122 system and other PS4\u2122 systems when signed in with that account.<br><br>Copyright 2014-2018 Sprakelsoft GmbH","macross-brain-context":"game","media-list":{"preview":[{"url":"https:\/\/apollo.dl.playstation.net\/cdn\/UP4786\/CUSA14158_00\/Q30qGieQk5HOeZ7spiF4z8hLjTldmGDU.mp4"}],"promo":{"images":[],"videos":[]},"screenshots":[{"url":"http:\/\/apollo.dl.playstation.net\/cdn\/UP4786\/CUSA14158_00\/hmehs23DPQpPUqughJunrLq3xH2AKnms.png"},{"url":"http:\/\/apollo.dl.playstation.net\/cdn\/UP4786\/CUSA14158_00\/1dfQOMJiwOJxa4gOq9XA5x4lcn3puCcN.png"},{"url":"http:\/\/apollo.dl.playstation.net\/cdn\/UP4786\/CUSA14158_00\/Rz4Jf5dgpgo1UJZKnai0G0rX4ivAfODc.png"},{"url":"http:\/\/apollo.dl.playstation.net\/cdn\/UP4786\/CUSA14158_00\/ZPJ2POZuqLsYqmdxnrJZi1pQ3UgpMkv6.png"},{"url":"http:\/\/apollo.dl.playstation.net\/cdn\/UP4786\/CUSA14158_00\/BcOHDjWyd4YVSU91POvW18MaTNSj8qS5.png"},{"url":"http:\/\/apollo.dl.playstation.net\/cdn\/UP4786\/CUSA14158_00\/7ZYB8Ho3yzlulldCjCG4dNze3JR1jfWa.png"}]},"name":"Croc's World","nsx-confirm-message":"","parent":null,"platforms":["PS4"],"plus-reward-description":null,"primary-classification":"DOWNLOADABLE_GAME","provider-name":"Sprakelsoft GmbH","ps-camera-compatibility":"incompatible","ps-move-compatibility":"incompatible","ps-vr-compatibility":"incompatible","release-date":"2018-11-02T00:00:00Z","secondary-classification":"GAME","skus":[{"entitlements":[{"duration":0,"exp-after-first-use":0}],"id":"UP4786-CUSA14158_00-CW1PS47890123456-U001","is-preorder":false,"multibuy":null,"name":"Full Game","playability-date":"","plus-reward-description":null,"prices":{"non-plus-user":{"actual-price":{"display":"$5.99","value":599},"availability":{"end-date":null,"start-date":null},"discount-percentage":0,"is-plus":false,"strikethrough-price":null,"upsell-price":null},"plus-user":{"actual-price":{"display":"$5.99","value":599},"availability":{"end-date":null,"start-date":null},"discount-percentage":0,"is-plus":false,"strikethrough-price":null,"upsell-price":null}}}],"star-rating":{"score":3.22,"total":9},"subtitle-language-codes":[],"tertiary-classification":"NA","thumbnail-url-base":"https:\/\/store.playstation.com\/store\/api\/chihiro\/00_09_000\/container\/US\/en\/999\/UP4786-CUSA14158_00-CW1PS47890123456\/1542133211000\/image","top-category":"downloadable_game","upsell-info":null,"voice-language-codes":[]},"id":"UP4786-CUSA14158_00-CW1PS47890123456","relationships":{"children":{"data":[{"id":"UP4786-CUSA14158_00-CROCSWORLDDEMO00","type":"game"}]},"legacy-skus":{"data":[{"id":"UP4786-CUSA14158_00-CW1PS47890123456-U001","type":"legacy-sku"}]}},"type":"game"}