{"id":111475,"name":"Castle Rencounter","slug":"castle-rencounter","url":"https:\/\/www.igdb.com\/games\/castle-rencounter","created_at":1540795317958,"updated_at":1541933306121,"summary":"What? These insolent decided to defend themselves and gather an army? How? Is their army going on the offensive? Can not be! Well, in this case, act, my lord. Smash the enemies and destroy their stronghold!","popularity":1,"games":[26298,36334,110098,28277,55282,81275,37419,68450,61616,75808],"tags":[268435487,268435488],"category":0,"game_modes":[1],"genres":[31,32],"screenshots":[{"url":"\/\/images.igdb.com\/igdb\/image\/upload\/t_thumb\/sc5k2b.jpg","cloudinary_id":"sc5k2b","width":1920,"height":1018},{"url":"\/\/images.igdb.com\/igdb\/image\/upload\/t_thumb\/sc5k2a.jpg","cloudinary_id":"sc5k2a","width":1920,"height":1018},{"url":"\/\/images.igdb.com\/igdb\/image\/upload\/t_thumb\/sc5k29.jpg","cloudinary_id":"sc5k29","width":1920,"height":1018},{"url":"\/\/images.igdb.com\/igdb\/image\/upload\/t_thumb\/sc5k28.jpg","cloudinary_id":"sc5k28","width":1920,"height":1018},{"url":"\/\/images.igdb.com\/igdb\/image\/upload\/t_thumb\/sc5k27.jpg","cloudinary_id":"sc5k27","width":1920,"height":1018}],"websites":[{"category":1,"url":"http:\/\/13-lab.ru\/"},{"category":13,"url":"https:\/\/store.steampowered.com\/app\/970620"}],"external":{"steam":"970620"}}