{"id":65737,"name":"Dragon Force: The Day 3","slug":"dragon-force-the-day-3","url":"https:\/\/www.igdb.com\/games\/dragon-force-the-day-3","created_at":1505297670451,"updated_at":1515850709946,"summary":"The sequel to The Day II and one of Mirinae Software's best selling games.","popularity":1.333333333333333,"games":[68287,71455,10209,10213,26766,36950,25300,74786,74782,70403],"tags":[18,536871078,536871882],"category":0,"keywords":[166,970],"themes":[18],"cover":{"url":"\/\/images.igdb.com\/igdb\/image\/upload\/t_thumb\/mcgy4bqhoxk0irwb8ozq.jpg","cloudinary_id":"mcgy4bqhoxk0irwb8ozq","width":700,"height":912}}