{"id":63372,"name":"Oni III: Kuro no Hakaishin","slug":"oni-iii-kuro-no-hakaishin","url":"https:\/\/www.igdb.com\/games\/oni-iii-kuro-no-hakaishin","created_at":1505088567557,"updated_at":1516735100839,"summary":"The third Oni RPG title for Game Boy.","collection":3339,"popularity":1.333333333333333,"games":[69505,12632,26766,27209,18398,57296,36926,36534,68324,80485],"tags":[536871208,536871938],"category":0,"keywords":[296,1026],"cover":{"url":"\/\/images.igdb.com\/igdb\/image\/upload\/t_thumb\/bqvb7y3ohmd4vuob3rdn.jpg","cloudinary_id":"bqvb7y3ohmd4vuob3rdn","width":329,"height":384}}