{"id":45436,"name":"Angelique Special","slug":"angelique-special","url":"https:\/\/www.igdb.com\/games\/angelique-special","created_at":1499506558328,"updated_at":1513470025622,"summary":"Angelique Special is a renovated version of Koei's first Angelique game, Angelique Special featured several new animated scenes, in addition to voice acting by several big-name voice actors. This version appeared on PC-FX, Sega Saturn, and Sony PlayStation, plus a hard-to-find PC version. Among the new animated scenes were several love events that were not present in the original game. Others included the opening sequence and the endings. \n \nThis is also the first (and currently only) title in the Angelique series to have an official translation: a Chinese language version exists for PC.","collection":3941,"franchise":1171,"franchises":[1171],"popularity":1.333333333333333,"developers":[630],"publishers":[2809],"category":0,"first_release_date":819590400000,"platforms":[6,86,32,7],"release_dates":[{"category":0,"platform":6,"date":828057600000,"region":5,"human":"1996-Mar-29","y":1996,"m":3},{"category":0,"platform":86,"date":819590400000,"region":5,"human":"1995-Dec-22","y":1995,"m":12},{"category":0,"platform":32,"date":828057600000,"region":5,"human":"1996-Mar-29","y":1996,"m":3},{"category":0,"platform":7,"date":828057600000,"region":5,"human":"1996-Mar-29","y":1996,"m":3}],"cover":{"url":"\/\/images.igdb.com\/igdb\/image\/upload\/t_thumb\/etfxom5jpbomgkxwkw1n.jpg","cloudinary_id":"etfxom5jpbomgkxwkw1n","width":640,"height":841}}