{"id":59144,"name":"Until the last","slug":"until-the-last","url":"https:\/\/www.igdb.com\/games\/until-the-last","created_at":1504773203084,"updated_at":1523329234674,"summary":"Horror with elements of detective...","popularity":1.333333333333333,"games":[28465,40524,34919,33603,36962,55888,44087,65827,28277,32283],"tags":[268435488],"category":0,"game_modes":[1],"genres":[32],"first_release_date":1505088000000,"platforms":[6],"release_dates":[{"category":0,"platform":6,"date":1505088000000,"region":8,"human":"2017-Sep-11","y":2017,"m":9}],"screenshots":[{"url":"\/\/images.igdb.com\/igdb\/image\/upload\/t_thumb\/nr3gdy4x2ybayqxrfog9.jpg","cloudinary_id":"nr3gdy4x2ybayqxrfog9","width":1416,"height":794},{"url":"\/\/images.igdb.com\/igdb\/image\/upload\/t_thumb\/qjkm0qqykozqlmeiv3sk.jpg","cloudinary_id":"qjkm0qqykozqlmeiv3sk","width":1416,"height":794},{"url":"\/\/images.igdb.com\/igdb\/image\/upload\/t_thumb\/fduvvvx966bykp7dvl3i.jpg","cloudinary_id":"fduvvvx966bykp7dvl3i","width":1416,"height":794},{"url":"\/\/images.igdb.com\/igdb\/image\/upload\/t_thumb\/yylom8w37b2ehbs5qfe2.jpg","cloudinary_id":"yylom8w37b2ehbs5qfe2","width":1416,"height":794},{"url":"\/\/images.igdb.com\/igdb\/image\/upload\/t_thumb\/fudmpnmadsr2drr39rfh.jpg","cloudinary_id":"fudmpnmadsr2drr39rfh","width":1233,"height":626}],"websites":[{"category":13,"url":"https:\/\/store.steampowered.com\/app\/709560"}],"external":{"steam":"709560"}}